jaxellip/__init__.py
jaxellip/elliptic_functions_and_integrals.py
jaxellip-0.0.1.dist-info/METADATA
jaxellip-0.0.1.dist-info/WHEEL
jaxellip-0.0.1.dist-info/licenses/LICENSE
jaxellip-0.0.1.dist-info/RECORD
