Metadata-Version: 2.4
Name: jaxellip
Version: 0.0.1
Summary: Some elliptic integrals in JAX
Project-URL: Source, https://github.com/sinaatalay/jaxellip
Author-email: Sina Atalay <dev@atalay.biz>
License-Expression: MIT
License-File: LICENSE
Classifier: Intended Audience :: Education
Classifier: Intended Audience :: Science/Research
Classifier: Programming Language :: Python :: 3.10
Classifier: Programming Language :: Python :: 3.11
Classifier: Programming Language :: Python :: 3.12
Classifier: Programming Language :: Python :: 3.13
Requires-Python: >=3.10
Requires-Dist: jax>=0.6.0
